tellurio/__init__.py
tellurio-0.0.0.dist-info/METADATA
tellurio-0.0.0.dist-info/WHEEL
tellurio-0.0.0.dist-info/top_level.txt
tellurio-0.0.0.dist-info/RECORD
