Metadata-Version: 2.4
Name: tellurio
Version: 0.0.0
Summary: Coming soon
Author-email: Your Name <you@example.com>
